[
    {
      "title": "สายสีเขียวและสายสีทอง",
      "company": "บริษัท ระบบขนส่งมวลชนกรุงเทพ จำกัด (มหาชน)",
      "address": "อาคารบีทีเอส 1000 ถนนพหลโยธิน เขตจตุจักร กรุงเทพมหานคร 10900",
      "phone": "โทร: 0 2617 7300",
      "fax": "แฟกซ์: 0 2617 7133, 0 2617 7155",
      "email": "อีเมล: nuduan@bts.co.th",
      "color": "green"
    },
    {
      "title": "สายสีเหลือง",
      "company": "บริษัท อีสเทิร์น บางกอกไมนเรล จำกัด",
      "address": "เลขที่ 21 ซอยเฉพาะทาง ถนนวิภาวดี-รังสิต เขตจอมพล กรุงเทพมหานคร 10900",
      "phone": "โทร: 0 2617 6111",
      "fax": "แฟกซ์: -",
      "email": "อีเมล: yellowline@ebm.co.th",
      "color": "yellow"
    },
    {
      "title": "สายสีชมพู",
      "company": "บริษัท นอร์ทเทิร์น บางกอกไมนเรล จำกัด",
      "address": "เลขที่ 21 ซอยเฉพาะทาง ถนนวิภาวดี-รังสิต เขตจอมพล กรุงเทพมหานคร 10900",
      "phone": "โทร: 0 2617 6111",
      "fax": "แฟกซ์: -",
      "email": "อีเมล: pinkline@nbm.co.th",
      "color": "pink"
    }
  ]
  